tomyam/__init__.py
tomyam/assetmanager/__init__.py
tomyam/assetmanager/dbmanager.py
tomyam-0.1.2.dist-info/WHEEL
tomyam-0.1.2.dist-info/METADATA
tomyam-0.1.2.dist-info/RECORD
