Metadata-Version: 2.1
Name: tomyam
Version: 0.1.2
Summary: 
Author: monarchjuno
Author-email: monarchjuno@gmail.com
Requires-Python: >=3.9,<4.0
Classifier: Programming Language :: Python :: 3
Classifier: Programming Language :: Python :: 3.10
Classifier: Programming Language :: Python :: 3.9
Requires-Dist: SQLAlchemy (>=1.4.39,<2.0.0)
Requires-Dist: pandas (>=1.4.3,<2.0.0)
